rindcalc/__init__.py
rindcalc/landsat.py
rindcalc/naip.py
rindcalc/sentinel.py
rindcalc/utils/__init__.py
rindcalc/utils/gen_stats.py
rindcalc/utils/norm.py
rindcalc/utils/resample.py
rindcalc/utils/save_index.py
tests/__init__.py
tests/test_landsat.py
tests/test_naip.py
tests/test_sent.py
tests/test_utils.py
rindcalc-3.0.0.dist-info/LICENSE
rindcalc-3.0.0.dist-info/METADATA
rindcalc-3.0.0.dist-info/WHEEL
rindcalc-3.0.0.dist-info/top_level.txt
rindcalc-3.0.0.dist-info/RECORD
