Metadata-Version: 2.1
Name: rindcalc
Version: 3.0.0
Summary: Rindcalc is an open source python package created to calculateremote-sensing indices and composites.
Home-page: https://github.com/ocsmit/rindcalc
Author: Owen Smith
Author-email: owen8461@protonmail.com
License: GNU 3.0
Platform: UNKNOWN
Classifier: Development Status :: 4 - Beta
Classifier: License :: OSI Approved :: MIT License
Classifier: Programming Language :: Python
Classifier: Programming Language :: Python :: 3.5
Classifier: Programming Language :: Python :: 3.6
Classifier: Programming Language :: Python :: 3.7
Classifier: Programming Language :: Python :: 3.8
Classifier: Topic :: Software Development :: Libraries
Classifier: Topic :: Software Development :: Libraries :: Python Modules
Classifier: Topic :: Scientific/Engineering :: GIS
Classifier: Intended Audience :: Science/Research
Requires-Python: >=3.5
Requires-Dist: numpy
Requires-Dist: gdal
